neckenml/__init__.py
neckenml/analyzer/__init__.py
neckenml/analyzer/audio_analyzer.py
neckenml/analyzer/folk_authenticity.py
neckenml/analyzer/reanalysis.py
neckenml/analyzer/extractors/__init__.py
neckenml/analyzer/extractors/feel.py
neckenml/analyzer/extractors/rhythm.py
neckenml/analyzer/extractors/section_labeler.py
neckenml/analyzer/extractors/structure.py
neckenml/analyzer/extractors/swing.py
neckenml/analyzer/extractors/vocal.py
neckenml/classifier/__init__.py
neckenml/classifier/params.py
neckenml/classifier/style_classifier.py
neckenml/classifier/style_head.py
neckenml/models/__init__.py
neckenml/models/schema.py
neckenml/models/pretrained/custom_style_head.pkl
neckenml/sources/__init__.py
neckenml/sources/base.py
neckenml/sources/file_source.py
neckenml/training/__init__.py
neckenml/training/trainer.py
neckenml_analyzer-0.2.0.dist-info/LICENSE
neckenml_analyzer-0.2.0.dist-info/METADATA
neckenml_analyzer-0.2.0.dist-info/WHEEL
neckenml_analyzer-0.2.0.dist-info/top_level.txt
neckenml_analyzer-0.2.0.dist-info/RECORD
