Metadata-Version: 2.2
Name: neckenml-analyzer
Version: 0.2.0
Summary: Swedish folk music audio analysis and dance style classification
Author: NeckenML Contributors
License: MIT
Project-URL: Homepage, https://github.com/svnoak/neckenml-analyzer
Project-URL: Documentation, https://github.com/svnoak/neckenml-analyzer/blob/main/README.md
Project-URL: Repository, https://github.com/svnoak/neckenml-analyzer
Project-URL: Issues, https://github.com/svnoak/neckenml-analyzer/issues
Keywords: audio,music,folk,swedish,classification,dance,analysis
Classifier: Development Status :: 3 - Alpha
Classifier: Intended Audience :: Developers
Classifier: Intended Audience :: Science/Research
Classifier: License :: OSI Approved :: MIT License
Classifier: Programming Language :: Python :: 3
Classifier: Programming Language :: Python :: 3.9
Classifier: Programming Language :: Python :: 3.10
Classifier: Programming Language :: Python :: 3.11
Classifier: Topic :: Multimedia :: Sound/Audio :: Analysis
Classifier: Topic :: Scientific/Engineering :: Artificial Intelligence
Requires-Python: >=3.9
License-File: LICENSE
Requires-Dist: numpy>=1.20.0
Requires-Dist: scikit-learn>=1.0.0
Requires-Dist: joblib>=1.0.0
Requires-Dist: sqlalchemy>=2.0.0
Requires-Dist: psycopg2-binary>=2.9.0
Requires-Dist: pgvector>=0.1.0
Provides-Extra: audio
Requires-Dist: essentia-tensorflow>=2.1b6.dev0; extra == "audio"
Requires-Dist: librosa>=0.9.0; extra == "audio"
Requires-Dist: madmom>=0.16.0; extra == "audio"
Requires-Dist: soundfile>=0.10.0; extra == "audio"
Provides-Extra: dev
Requires-Dist: pytest>=7.0.0; extra == "dev"
Requires-Dist: pytest-cov>=3.0.0; extra == "dev"
Requires-Dist: black>=22.0.0; extra == "dev"
Requires-Dist: flake8>=4.0.0; extra == "dev"
